{
  "entries": [
    {
      "serial": 109,
      "title": "中国人民银行令〔2025〕第9号（国库集中收付代理银行资格认定管理办法）",
      "remark": "2025-10-11",
      "documents": [
        {
          "type": "html",
          "url": "http://www.pbc.gov.cn/tiaofasi/144941/144957/5863410/index.html",
          "title": "中国人民银行令〔2025〕第9号（国库集中收付代理银行资格认定管理办法）",
          "downloaded": true,
          "local_path": "downloads/tiaofasi_departmental_rule/tiaofasi_departmental_rule_000109_001.html"
        },
        {
          "type": "pdf",
          "url": "http://www.pbc.gov.cn/tiaofasi/144941/144957/5863410/2025101110342430817.pdf",
          "title": "附件1：国库集中收付代理银行资格认定申请表.pdf",
          "downloaded": true,
          "local_path": "downloads/tiaofasi_departmental_rule/tiaofasi_departmental_rule_000109_002.pdf"
        },
        {
          "type": "pdf",
          "url": "http://www.pbc.gov.cn/tiaofasi/144941/144957/5863410/2025101110344136045.pdf",
          "title": "附件2：国库集中收付代理银行资格认定申请书主要内容.pdf",
          "downloaded": true,
          "local_path": "downloads/tiaofasi_departmental_rule/tiaofasi_departmental_rule_000109_003.pdf"
        }
      ]
    },
    {
      "serial": 108,
      "title": "中国人民银行令〔2025〕第8号（商业银行、信用社代理支库业务审批管理办法）",
      "remark": "2025-10-11",
      "documents": [
        {
          "type": "html",
          "url": "http://www.pbc.gov.cn/tiaofasi/144941/144957/5863367/index.html",
          "title": "中国人民银行令〔2025〕第8号（商业银行、信用社代理支库业务审批管理办法）",
          "downloaded": true,
          "local_path": "downloads/tiaofasi_departmental_rule/tiaofasi_departmental_rule_000108_001.html"
        },
        {
          "type": "pdf",
          "url": "http://www.pbc.gov.cn/tiaofasi/144941/144957/5863367/2025101110325372228.pdf",
          "title": "附件1：代理支库业务申请书.pdf",
          "downloaded": true,
          "local_path": "downloads/tiaofasi_departmental_rule/tiaofasi_departmental_rule_000108_002.pdf"
        },
        {
          "type": "pdf",
          "url": "http://www.pbc.gov.cn/tiaofasi/144941/144957/5863367/2025101110332081326.pdf",
          "title": "附件2：代理支库业务年审登记表.pdf",
          "downloaded": true,
          "local_path": "downloads/tiaofasi_departmental_rule/tiaofasi_departmental_rule_000108_003.pdf"
        }
      ]
    },
    {
      "serial": 100,
      "title": "中国人民银行令〔2002〕第9号（金融统计管理规定）",
      "remark": "2002-11-01",
      "documents": [
        {
          "type": "html",
          "url": "http://www.pbc.gov.cn/tiaofasi/144941/144957/3590903/index.html",
          "title": "中国人民银行令〔2002〕第9号（金融统计管理规定）",
          "downloaded": true,
          "local_path": "downloads/tiaofasi_departmental_rule/tiaofasi_departmental_rule_000100_001.html"
        },
        {
          "type": "pdf",
          "url": "http://www.pbc.gov.cn/tiaofasi/144941/144957/3590903/2018073109403535224.pdf",
          "title": "中国人民银行令〔2002〕第9号（金融统计管理规定）（中国人民银行令〔2002〕第9号）.pdf",
          "downloaded": true,
          "local_path": "downloads/tiaofasi_departmental_rule/tiaofasi_departmental_rule_000100_002.pdf"
        }
      ]
    },
    {
      "serial": 96,
      "title": "中国人民银行令〔2003〕第5号（人民币银行结算账户管理办法）",
      "remark": "2003-04-10",
      "documents": [
        {
          "type": "html",
          "url": "http://www.pbc.gov.cn/tiaofasi/144941/144957/3590886/index.html",
          "title": "中国人民银行令〔2003〕第5号（人民币银行结算账户管理办法）",
          "downloaded": true,
          "local_path": "downloads/tiaofasi_departmental_rule/tiaofasi_departmental_rule_000096_001.html"
        },
        {
          "type": "pdf",
          "url": "http://www.pbc.gov.cn/tiaofasi/144941/144957/3590886/2018073109334749880.pdf",
          "title": "中国人民银行令〔2003〕第5号（人民币银行结算账户管理办法）（中国人民银行令〔2003〕第5号）.pdf",
          "downloaded": true,
          "local_path": "downloads/tiaofasi_departmental_rule/tiaofasi_departmental_rule_000096_002.pdf"
        }
      ]
    },
    {
      "serial": 92,
      "title": "中国人民银行令〔2003〕第7号（中国人民银行残缺污损人民币兑换办法）",
      "remark": "2003-12-24",
      "documents": [
        {
          "type": "html",
          "url": "http://www.pbc.gov.cn/tiaofasi/144941/144957/3590880/index.html",
          "title": "中国人民银行令〔2003〕第7号（中国人民银行残缺污损人民币兑换办法）",
          "downloaded": true,
          "local_path": "downloads/tiaofasi_departmental_rule/tiaofasi_departmental_rule_000092_001.html"
        },
        {
          "type": "pdf",
          "url": "http://www.pbc.gov.cn/tiaofasi/144941/144957/3590880/2018073109303756863.pdf",
          "title": "中国人民银行令〔2003〕第7号（中国人民银行残缺污损人民币兑换办法）（中国人民银行令〔2003〕第7号）.pdf",
          "downloaded": true,
          "local_path": "downloads/tiaofasi_departmental_rule/tiaofasi_departmental_rule_000092_002.pdf"
        }
      ]
    },
    {
      "serial": 90,
      "title": "中国人民银行令〔2004〕第1号（全国银行间债券市场债券买断式回购业务管理规定）",
      "remark": "中国人民银行令〔2004〕第1号（全国银行间债券市场债券买断式回购业务管理规...",
      "documents": [
        {
          "type": "html",
          "url": "http://www.pbc.gov.cn/tiaofasi/144941/144957/3590875/index.html",
          "title": "中国人民银行令〔2004〕第1号（全国银行间债券市场债券买断式回购业务管理规定）",
          "downloaded": true,
          "local_path": "downloads/tiaofasi_departmental_rule/tiaofasi_departmental_rule_000090_001.html"
        },
        {
          "type": "pdf",
          "url": "http://www.pbc.gov.cn/tiaofasi/144941/144957/3590875/2018073109264993749.pdf",
          "title": "中国人民银行令〔2004〕第1号（全国银行间债券市场债券买断式回购业务管理规定）（中国人民银行令〔2004〕第1号）.pdf",
          "downloaded": true,
          "local_path": "downloads/tiaofasi_departmental_rule/tiaofasi_departmental_rule_000090_002.pdf"
        }
      ]
    },
    {
      "serial": 86,
      "title": "中国人民银行关于印发《离岸银行业务管理办法》的通知（银发〔1997〕438号）",
      "remark": "1997-10-29",
      "documents": [
        {
          "type": "html",
          "url": "http://www.pbc.gov.cn/tiaofasi/144941/144957/3601581/index.html",
          "title": "中国人民银行关于印发《离岸银行业务管理办法》的通知（银发〔1997〕438号）",
          "downloaded": true,
          "local_path": "downloads/tiaofasi_departmental_rule/tiaofasi_departmental_rule_000086_001.html"
        },
        {
          "type": "pdf",
          "url": "http://www.pbc.gov.cn/tiaofasi/144941/144957/3601581/2018081309081698595.pdf",
          "title": "中国人民银行关于印发《离岸银行业务管理办法》的通知（银发〔1997〕438号）.pdf",
          "downloaded": true,
          "local_path": "downloads/tiaofasi_departmental_rule/tiaofasi_departmental_rule_000086_002.pdf"
        }
      ]
    },
    {
      "serial": 85,
      "title": "关于印发《人民币单位存款管理办法》的通知（银发〔1997〕485号）",
      "remark": "1997-11-21",
      "documents": [
        {
          "type": "html",
          "url": "http://www.pbc.gov.cn/tiaofasi/144941/144957/3591323/index.html",
          "title": "关于印发《人民币单位存款管理办法》的通知（银发〔1997〕485号）",
          "downloaded": true,
          "local_path": "downloads/tiaofasi_departmental_rule/tiaofasi_departmental_rule_000085_001.html"
        },
        {
          "type": "pdf",
          "url": "http://www.pbc.gov.cn/tiaofasi/144941/144957/3591323/2018073114232687978.pdf",
          "title": "关于印发《人民币单位存款管理办法》的通知（银发〔1997〕485号）.pdf",
          "downloaded": true,
          "local_path": "downloads/tiaofasi_departmental_rule/tiaofasi_departmental_rule_000085_002.pdf"
        }
      ]
    },
    {
      "serial": 84,
      "title": "关于印发《通知存款管理办法》的通知（银发〔1999〕3号）",
      "remark": "1999-01-03",
      "documents": [
        {
          "type": "html",
          "url": "http://www.pbc.gov.cn/tiaofasi/144941/144957/3591347/index.html",
          "title": "关于印发《通知存款管理办法》的通知（银发〔1999〕3号）",
          "downloaded": true,
          "local_path": "downloads/tiaofasi_departmental_rule/tiaofasi_departmental_rule_000084_001.html"
        },
        {
          "type": "pdf",
          "url": "http://www.pbc.gov.cn/tiaofasi/144941/144957/3591347/2018073114315550543.pdf",
          "title": "关于印发《通知存款管理办法》的通知（银发〔1999〕3号）.pdf",
          "downloaded": true,
          "local_path": "downloads/tiaofasi_departmental_rule/tiaofasi_departmental_rule_000084_002.pdf"
        }
      ]
    },
    {
      "serial": 83,
      "title": "关于印发《人民币利率管理规定》的通知（银发〔1999〕77号）",
      "remark": "1999-03-03",
      "documents": [
        {
          "type": "html",
          "url": "http://www.pbc.gov.cn/tiaofasi/144941/144957/3591357/index.html",
          "title": "关于印发《人民币利率管理规定》的通知（银发〔1999〕77号）",
          "downloaded": true,
          "local_path": "downloads/tiaofasi_departmental_rule/tiaofasi_departmental_rule_000083_001.html"
        },
        {
          "type": "pdf",
          "url": "http://www.pbc.gov.cn/tiaofasi/144941/144957/3591357/2018073114432573360.pdf",
          "title": "关于印发《人民币利率管理规定》的通知（银发〔1999〕77号）.pdf",
          "downloaded": true,
          "local_path": "downloads/tiaofasi_departmental_rule/tiaofasi_departmental_rule_000083_002.pdf"
        }
      ]
    },
    {
      "serial": 82,
      "title": "关于印发《中国人民银行紧急贷款管理暂行办法》的通知（银发〔1999〕407号）",
      "remark": "1999-12-31",
      "documents": [
        {
          "type": "html",
          "url": "http://www.pbc.gov.cn/tiaofasi/144941/144957/3591379/index.html",
          "title": "关于印发《中国人民银行紧急贷款管理暂行办法》的通知（银发〔1999〕407号）",
          "downloaded": true,
          "local_path": "downloads/tiaofasi_departmental_rule/tiaofasi_departmental_rule_000082_001.html"
        },
        {
          "type": "pdf",
          "url": "http://www.pbc.gov.cn/tiaofasi/144941/144957/3591379/2018073115070999825.pdf",
          "title": "关于印发《中国人民银行紧急贷款管理暂行办法》的通知（银发〔1999〕407号）.pdf",
          "downloaded": true,
          "local_path": "downloads/tiaofasi_departmental_rule/tiaofasi_departmental_rule_000082_002.pdf"
        }
      ]
    },
    {
      "serial": 81,
      "title": "中国人民银行令〔2000〕第2号（全国银行间债券市场债券交易管理办法）",
      "remark": "2000-04-30",
      "documents": [
        {
          "type": "html",
          "url": "http://www.pbc.gov.cn/tiaofasi/144941/144957/3591384/index.html",
          "title": "中国人民银行令〔2000〕第2号（全国银行间债券市场债券交易管理办法）",
          "downloaded": true,
          "local_path": "downloads/tiaofasi_departmental_rule/tiaofasi_departmental_rule_000081_001.html"
        },
        {
          "type": "pdf",
          "url": "http://www.pbc.gov.cn/tiaofasi/144941/144957/3591384/2018073115112165688.pdf",
          "title": "中国人民银行令〔2000〕第2号（全国银行间债券市场债券交易管理办法）（中国人民银行令〔2000〕第2号）.pdf",
          "downloaded": true,
          "local_path": "downloads/tiaofasi_departmental_rule/tiaofasi_departmental_rule_000081_002.pdf"
        }
      ]
    },
    {
      "serial": 80,
      "title": "关于印发《地方政府向中央专项借款管理规定》的通知（银发〔2000〕148号）",
      "remark": "2000-05-16",
      "documents": [
        {
          "type": "html",
          "url": "http://www.pbc.gov.cn/tiaofasi/144941/144957/3591399/index.html",
          "title": "关于印发《地方政府向中央专项借款管理规定》的通知（银发〔2000〕148号）",
          "downloaded": true,
          "local_path": "downloads/tiaofasi_departmental_rule/tiaofasi_departmental_rule_000080_001.html"
        },
        {
          "type": "pdf",
          "url": "http://www.pbc.gov.cn/tiaofasi/144941/144957/3591399/2018073115154842098.pdf",
          "title": "关于印发《地方政府向中央专项借款管理规定》的通知（银发〔2000〕148号）.pdf",
          "downloaded": true,
          "local_path": "downloads/tiaofasi_departmental_rule/tiaofasi_departmental_rule_000080_002.pdf"
        }
      ]
    },
    {
      "serial": 79,
      "title": "支付结算业务代理办法（银发〔2000〕176号）",
      "remark": "2000-06-01",
      "documents": [
        {
          "type": "html",
          "url": "http://www.pbc.gov.cn/tiaofasi/144941/144957/3591404/index.html",
          "title": "支付结算业务代理办法（银发〔2000〕176号）",
          "downloaded": true,
          "local_path": "downloads/tiaofasi_departmental_rule/tiaofasi_departmental_rule_000079_001.html"
        },
        {
          "type": "pdf",
          "url": "http://www.pbc.gov.cn/tiaofasi/144941/144957/3591404/2018073115185899371.pdf",
          "title": "支付结算业务代理办法（银发〔2000〕176号）.pdf",
          "downloaded": true,
          "local_path": "downloads/tiaofasi_departmental_rule/tiaofasi_departmental_rule_000079_002.pdf"
        }
      ]
    },
    {
      "serial": 74,
      "title": "中国人民银行令〔2001〕第1号（商业银行、信用社代理国库业务管理办法）",
      "remark": "2001-01-09",
      "documents": [
        {
          "type": "html",
          "url": "http://www.pbc.gov.cn/tiaofasi/144941/144957/3590937/index.html",
          "title": "中国人民银行令〔2001〕第1号（商业银行、信用社代理国库业务管理办法）",
          "downloaded": true,
          "local_path": "downloads/tiaofasi_departmental_rule/tiaofasi_departmental_rule_000074_001.html"
        },
        {
          "type": "pdf",
          "url": "http://www.pbc.gov.cn/tiaofasi/144941/144957/3590937/2018073109572675797.pdf",
          "title": "中国人民银行令〔2001〕第1号（商业银行、信用社代理国库业务管理办法）（中国人民银行令〔2001〕第1号）.pdf",
          "downloaded": true,
          "local_path": "downloads/tiaofasi_departmental_rule/tiaofasi_departmental_rule_000074_002.pdf"
        }
      ]
    },
    {
      "serial": 70,
      "title": "中国人民银行令〔2001〕第3号（中国人民银行行政处罚程序规定）",
      "remark": "2001-02-01",
      "documents": [
        {
          "type": "html",
          "url": "http://www.pbc.gov.cn/tiaofasi/144941/144957/3590927/index.html",
          "title": "中国人民银行令〔2001〕第3号（中国人民银行行政处罚程序规定）",
          "downloaded": true,
          "local_path": "downloads/tiaofasi_departmental_rule/tiaofasi_departmental_rule_000070_001.html"
        },
        {
          "type": "pdf",
          "url": "http://www.pbc.gov.cn/tiaofasi/144941/144957/3590927/2018073109540785923.pdf",
          "title": "中国人民银行令〔2001〕第3号（中国人民银行行政处罚程序规定）（中国人民银行令〔2001〕第3号）.pdf",
          "downloaded": true,
          "local_path": "downloads/tiaofasi_departmental_rule/tiaofasi_departmental_rule_000070_002.pdf"
        }
      ]
    },
    {
      "serial": 69,
      "title": "中国人民银行令〔2001〕第4号（中国人民银行行政复议办法）",
      "remark": "2001-02-01",
      "documents": [
        {
          "type": "html",
          "url": "http://www.pbc.gov.cn/tiaofasi/144941/144957/3590913/index.html",
          "title": "中国人民银行令〔2001〕第4号（中国人民银行行政复议办法）",
          "downloaded": true,
          "local_path": "downloads/tiaofasi_departmental_rule/tiaofasi_departmental_rule_000069_001.html"
        },
        {
          "type": "pdf",
          "url": "http://www.pbc.gov.cn/tiaofasi/144941/144957/3590913/2018073109505312445.pdf",
          "title": "中国人民银行令〔2001〕第4号（中国人民银行行政复议办法）（中国人民银行令〔2001〕第4号）.pdf",
          "downloaded": true,
          "local_path": "downloads/tiaofasi_departmental_rule/tiaofasi_departmental_rule_000069_002.pdf"
        }
      ]
    },
    {
      "serial": 62,
      "title": "中国人民银行令〔2006〕第3号（个人外汇管理办法）",
      "remark": "2006-12-25",
      "documents": [
        {
          "type": "html",
          "url": "http://www.pbc.gov.cn/tiaofasi/144941/144957/3590787/index.html",
          "title": "中国人民银行令〔2006〕第3号（个人外汇管理办法）",
          "downloaded": true,
          "local_path": "downloads/tiaofasi_departmental_rule/tiaofasi_departmental_rule_000062_001.html"
        },
        {
          "type": "pdf",
          "url": "http://www.pbc.gov.cn/tiaofasi/144941/144957/3590787/2018073109014552779.pdf",
          "title": "中国人民银行令〔2006〕第3号（个人外汇管理办法）（中国人民银行令〔2006〕第3号）.pdf",
          "downloaded": true,
          "local_path": "downloads/tiaofasi_departmental_rule/tiaofasi_departmental_rule_000062_002.pdf"
        }
      ]
    },
    {
      "serial": 61,
      "title": "中国人民银行 中国银行业监督管理委员会 中国证券监督管理委员会 中国保险监督管理委员会令〔2007〕第2号（金融机构客户身份识别和客户身份资料及交易记录保存管理办法）",
      "remark": "中国人民银行 中国银行业监督管理委员会 中国证券监督管理委员会 中国保险监...",
      "documents": [
        {
          "type": "html",
          "url": "http://www.pbc.gov.cn/tiaofasi/144941/144957/2817396/index.html",
          "title": "中国人民银行 中国银行业监督管理委员会 中国证券监督管理委员会 中国保险监督管理委员会令〔2007〕第2号（金融机构客户身份识别和客户身份资料及交易记录保存管理办法）",
          "downloaded": true,
          "local_path": "downloads/tiaofasi_departmental_rule/tiaofasi_departmental_rule_000061_001.html"
        },
        {
          "type": "pdf",
          "url": "http://www.pbc.gov.cn/eportal/fileDir/history_file/files/att_13928_1.pdf",
          "title": "中国人民银行　中国银行业监督管理委员会　中国证券监督管理委员会　中国保险监督管理委员会令〔2007〕第2号.pdf",
          "downloaded": true,
          "local_path": "downloads/tiaofasi_departmental_rule/tiaofasi_departmental_rule_000061_002.pdf"
        }
      ]
    },
    {
      "serial": 59,
      "title": "中国人民银行令〔2008〕第1号（银行间债券市场非金融企业债务融资工具管理办法）",
      "remark": "中国人民银行令〔2008〕第1号（银行间债券市场非金融企业债务融资工具管理办...",
      "documents": [
        {
          "type": "html",
          "url": "http://www.pbc.gov.cn/tiaofasi/144941/144957/3590807/index.html",
          "title": "中国人民银行令〔2008〕第1号（银行间债券市场非金融企业债务融资工具管理办法）",
          "downloaded": true,
          "local_path": "downloads/tiaofasi_departmental_rule/tiaofasi_departmental_rule_000059_001.html"
        },
        {
          "type": "pdf",
          "url": "http://www.pbc.gov.cn/tiaofasi/144941/144957/3590807/2018073109050799935.pdf",
          "title": "中国人民银行令〔2008〕第1号（银行间债券市场非金融企业债务融资工具管理办法）（中国人民银行令〔2008〕第1号）.pdf",
          "downloaded": true,
          "local_path": "downloads/tiaofasi_departmental_rule/tiaofasi_departmental_rule_000059_002.pdf"
        }
      ]
    },
    {
      "serial": 58,
      "title": "中国人民银行令〔2009〕第1号（银行间债券市场债券登记托管结算管理办法）",
      "remark": "2009-09-26",
      "documents": [
        {
          "type": "html",
          "url": "http://www.pbc.gov.cn/tiaofasi/144941/144957/3590824/index.html",
          "title": "中国人民银行令〔2009〕第1号（银行间债券市场债券登记托管结算管理办法）",
          "downloaded": true,
          "local_path": "downloads/tiaofasi_departmental_rule/tiaofasi_departmental_rule_000058_001.html"
        },
        {
          "type": "pdf",
          "url": "http://www.pbc.gov.cn/tiaofasi/144941/144957/3590824/2018073109081659929.pdf",
          "title": "中国人民银行令〔2009〕第1号（银行间债券市场债券登记托管结算管理办法）（中国人民银行令〔2009〕第1号）.pdf",
          "downloaded": true,
          "local_path": "downloads/tiaofasi_departmental_rule/tiaofasi_departmental_rule_000058_002.pdf"
        }
      ]
    },
    {
      "serial": 57,
      "title": "中国人民银行令〔2009〕第2号（电子商业汇票业务管理办法）",
      "remark": "2009-10-16",
      "documents": [
        {
          "type": "html",
          "url": "http://www.pbc.gov.cn/tiaofasi/144941/144957/3590844/index.html",
          "title": "中国人民银行令〔2009〕第2号（电子商业汇票业务管理办法）",
          "downloaded": true,
          "local_path": "downloads/tiaofasi_departmental_rule/tiaofasi_departmental_rule_000057_001.html"
        },
        {
          "type": "pdf",
          "url": "http://www.pbc.gov.cn/tiaofasi/144941/144957/3590844/2018073109121392042.pdf",
          "title": "中国人民银行令〔2009〕第2号（电子商业汇票业务管理办法）（中国人民银行令〔2009〕第2号）.pdf",
          "downloaded": true,
          "local_path": "downloads/tiaofasi_departmental_rule/tiaofasi_departmental_rule_000057_002.pdf"
        }
      ]
    },
    {
      "serial": 52,
      "title": "中国人民银行 海关总署令〔2015〕第1号（黄金及黄金制品进出口管理办法）",
      "remark": "2015-03-04",
      "documents": [
        {
          "type": "html",
          "url": "http://www.pbc.gov.cn/tiaofasi/144941/144957/2811341/index.html",
          "title": "中国人民银行 海关总署令〔2015〕第1号（黄金及黄金制品进出口管理办法）",
          "downloaded": true,
          "local_path": "downloads/tiaofasi_departmental_rule/tiaofasi_departmental_rule_000052_001.html"
        },
        {
          "type": "pdf",
          "url": "http://www.pbc.gov.cn/tiaofasi/144941/144957/2811341/2018073016461740250.pdf",
          "title": "中国人民银行 海关总署令〔2015〕第1号（黄金及黄金制品进出口管理办法）（中国人民银行 海关总署令〔2015〕第1号）.pdf",
          "downloaded": true,
          "local_path": "downloads/tiaofasi_departmental_rule/tiaofasi_departmental_rule_000052_002.pdf"
        }
      ]
    },
    {
      "serial": 50,
      "title": "中国人民银行令〔2016〕第3号（金融机构大额交易和可疑交易报告管理办法）",
      "remark": "2016-12-28",
      "documents": [
        {
          "type": "html",
          "url": "http://www.pbc.gov.cn/tiaofasi/144941/144957/3631415/index.html",
          "title": "中国人民银行令〔2016〕第3号（金融机构大额交易和可疑交易报告管理办法）",
          "downloaded": true,
          "local_path": "downloads/tiaofasi_departmental_rule/tiaofasi_departmental_rule_000050_001.html"
        },
        {
          "type": "pdf",
          "url": "http://www.pbc.gov.cn/tiaofasi/144941/144957/3631415/2018091916273063902.pdf",
          "title": "中国人民银行令〔2016〕第3号（金融机构大额交易和可疑交易报告管理办法）.pdf",
          "downloaded": true,
          "local_path": "downloads/tiaofasi_departmental_rule/tiaofasi_departmental_rule_000050_002.pdf"
        }
      ]
    },
    {
      "serial": 49,
      "title": "中国人民银行令〔2017〕第1号（内地与香港债券市场互联互通合作管理暂行办法）",
      "remark": "中国人民银行令〔2017〕第1号（内地与香港债券市场互联互通合作管理暂行办法...",
      "documents": [
        {
          "type": "html",
          "url": "http://www.pbc.gov.cn/tiaofasi/144941/144957/3590853/index.html",
          "title": "中国人民银行令〔2017〕第1号（内地与香港债券市场互联互通合作管理暂行办法）",
          "downloaded": true,
          "local_path": "downloads/tiaofasi_departmental_rule/tiaofasi_departmental_rule_000049_001.html"
        },
        {
          "type": "pdf",
          "url": "http://www.pbc.gov.cn/tiaofasi/144941/144957/3590853/2018073109160698641.pdf",
          "title": "中国人民银行令〔2017〕第1号（内地与香港债券市场互联互通合作管理暂行办法）（中国人民银行令〔2017〕第1号）.pdf",
          "downloaded": true,
          "local_path": "downloads/tiaofasi_departmental_rule/tiaofasi_departmental_rule_000049_002.pdf"
        }
      ]
    },
    {
      "serial": 48,
      "title": "中国人民银行 中国银行业监督管理委员会令〔2017〕第2号（汽车贷款管理办法）",
      "remark": "中国人民银行 中国银行业监督管理委员会令〔2017〕第2号（汽车贷款管理办法...",
      "documents": [
        {
          "type": "html",
          "url": "http://www.pbc.gov.cn/tiaofasi/144941/144957/3590858/index.html",
          "title": "中国人民银行 中国银行业监督管理委员会令〔2017〕第2号（汽车贷款管理办法）",
          "downloaded": true,
          "local_path": "downloads/tiaofasi_departmental_rule/tiaofasi_departmental_rule_000048_001.html"
        },
        {
          "type": "pdf",
          "url": "http://www.pbc.gov.cn/tiaofasi/144941/144957/3590858/2018073109200583794.pdf",
          "title": "中国人民银行 中国银行业监督管理委员会令〔2017〕第2号（汽车贷款管理办法）（中国人民银行 中国银行业监督管理委员会令〔2017〕第2号）.pdf",
          "downloaded": true,
          "local_path": "downloads/tiaofasi_departmental_rule/tiaofasi_departmental_rule_000048_002.pdf"
        }
      ]
    },
    {
      "serial": 47,
      "title": "中国人民银行令〔2017〕第3号（应收账款质押登记办法）",
      "remark": "2017-10-25",
      "documents": [
        {
          "type": "html",
          "url": "http://www.pbc.gov.cn/tiaofasi/144941/144957/3590864/index.html",
          "title": "中国人民银行令〔2017〕第3号（应收账款质押登记办法）",
          "downloaded": true,
          "local_path": "downloads/tiaofasi_departmental_rule/tiaofasi_departmental_rule_000047_001.html"
        },
        {
          "type": "pdf",
          "url": "http://www.pbc.gov.cn/tiaofasi/144941/144957/3590864/2018073109224797284.pdf",
          "title": "中国人民银行令〔2017〕第3号（应收账款质押登记办法）（中国人民银行令〔2017〕第3号）.pdf",
          "downloaded": true,
          "local_path": "downloads/tiaofasi_departmental_rule/tiaofasi_departmental_rule_000047_002.pdf"
        }
      ]
    },
    {
      "serial": 46,
      "title": "中国人民银行 中华人民共和国海关总署关于印发《对金银进出国境的管理办法》的通知（（84）银发字第13号）",
      "remark": "中国人民银行 中华人民共和国海关总署关于印发《对金银进出国境的管理办法...",
      "documents": [
        {
          "type": "html",
          "url": "http://www.pbc.gov.cn/tiaofasi/144941/144957/3591036/index.html",
          "title": "中国人民银行 中华人民共和国海关总署关于印发《对金银进出国境的管理办法》的通知（（84）银发字第13号）",
          "downloaded": true,
          "local_path": "downloads/tiaofasi_departmental_rule/tiaofasi_departmental_rule_000046_001.html"
        },
        {
          "type": "pdf",
          "url": "http://www.pbc.gov.cn/tiaofasi/144941/144957/3591036/2018073111015785616.pdf",
          "title": "中国人民银行 中华人民共和国海关总署关于印发《对金银进出国境的管理办法》的通知（（84）银发字第13号）.pdf",
          "downloaded": true,
          "local_path": "downloads/tiaofasi_departmental_rule/tiaofasi_departmental_rule_000046_002.pdf"
        }
      ]
    },
    {
      "serial": 45,
      "title": "中国人民银行关于执行《储蓄管理条例》的若干规定（银发〔1993〕7号）",
      "remark": "1993-01-14",
      "documents": [
        {
          "type": "html",
          "url": "http://www.pbc.gov.cn/tiaofasi/144941/144957/3591089/index.html",
          "title": "中国人民银行关于执行《储蓄管理条例》的若干规定（银发〔1993〕7号）",
          "downloaded": true,
          "local_path": "downloads/tiaofasi_departmental_rule/tiaofasi_departmental_rule_000045_001.html"
        },
        {
          "type": "pdf",
          "url": "http://www.pbc.gov.cn/tiaofasi/144941/144957/3591089/2018073111141136708.pdf",
          "title": "中国人民银行关于执行《储蓄管理条例》的若干规定（银发〔1993〕7号）.pdf",
          "downloaded": true,
          "local_path": "downloads/tiaofasi_departmental_rule/tiaofasi_departmental_rule_000045_002.pdf"
        }
      ]
    },
    {
      "serial": 44,
      "title": "中国人民银行关于印发《银行间外汇市场管理暂行规定》的通知（银发〔1996〕423号文印发）",
      "remark": "中国人民银行关于印发《银行间外汇市场管理暂行规定》的通知（银发〔1996〕...",
      "documents": [
        {
          "type": "html",
          "url": "http://www.pbc.gov.cn/tiaofasi/144941/144957/3591189/index.html",
          "title": "中国人民银行关于印发《银行间外汇市场管理暂行规定》的通知（银发〔1996〕423号文印发）",
          "downloaded": true,
          "local_path": "downloads/tiaofasi_departmental_rule/tiaofasi_departmental_rule_000044_001.html"
        },
        {
          "type": "pdf",
          "url": "http://www.pbc.gov.cn/tiaofasi/144941/144957/3591189/2018073111230512756.pdf",
          "title": "中国人民银行关于印发《银行间外汇市场管理暂行规定》的通知（银发〔1996〕423号文印发）.pdf",
          "downloaded": true,
          "local_path": "downloads/tiaofasi_departmental_rule/tiaofasi_departmental_rule_000044_002.pdf"
        }
      ]
    },
    {
      "serial": 43,
      "title": "中国人民银行关于印发《商业汇票承兑、贴现与再贴现管理暂行办法》的通知（银发〔1997〕216号）",
      "remark": "中国人民银行关于印发《商业汇票承兑、贴现与再贴现管理暂行办法》的通知（...",
      "documents": [
        {
          "type": "html",
          "url": "http://www.pbc.gov.cn/tiaofasi/144941/144957/3591225/index.html",
          "title": "中国人民银行关于印发《商业汇票承兑、贴现与再贴现管理暂行办法》的通知（银发〔1997〕216号）",
          "downloaded": true,
          "local_path": "downloads/tiaofasi_departmental_rule/tiaofasi_departmental_rule_000043_001.html"
        },
        {
          "type": "pdf",
          "url": "http://www.pbc.gov.cn/tiaofasi/144941/144957/3591225/2018073111335747707.pdf",
          "title": "中国人民银行关于印发《商业汇票承兑、贴现与再贴现管理暂行办法》的通知（银发〔1997〕216号）.pdf",
          "downloaded": true,
          "local_path": "downloads/tiaofasi_departmental_rule/tiaofasi_departmental_rule_000043_002.pdf"
        }
      ]
    },
    {
      "serial": 42,
      "title": "中国人民银行关于印发《支付结算办法》的通知（银发〔1997〕393号）",
      "remark": "1997-09-29",
      "documents": [
        {
          "type": "html",
          "url": "http://www.pbc.gov.cn/tiaofasi/144941/144957/3601571/index.html",
          "title": "中国人民银行关于印发《支付结算办法》的通知（银发〔1997〕393号）",
          "downloaded": true,
          "local_path": "downloads/tiaofasi_departmental_rule/tiaofasi_departmental_rule_000042_001.html"
        },
        {
          "type": "pdf",
          "url": "http://www.pbc.gov.cn/tiaofasi/144941/144957/3601571/2018081309061735002.pdf",
          "title": "中国人民银行关于印发《支付结算办法》的通知（银发〔1997〕393号）.pdf",
          "downloaded": true,
          "local_path": "downloads/tiaofasi_departmental_rule/tiaofasi_departmental_rule_000042_002.pdf"
        }
      ]
    },
    {
      "serial": 40,
      "title": "中国人民银行关于印发《境内外汇账户管理规定》的通知（银发〔1997〕416号）",
      "remark": "1997-10-10",
      "documents": [
        {
          "type": "html",
          "url": "http://www.pbc.gov.cn/tiaofasi/144941/144957/3601576/index.html",
          "title": "中国人民银行关于印发《境内外汇账户管理规定》的通知（银发〔1997〕416号）",
          "downloaded": true,
          "local_path": "downloads/tiaofasi_departmental_rule/tiaofasi_departmental_rule_000040_001.html"
        },
        {
          "type": "pdf",
          "url": "http://www.pbc.gov.cn/tiaofasi/144941/144957/3601576/2018081309073040411.pdf",
          "title": "中国人民银行关于印发《境内外汇账户管理规定》的通知（银发〔1997〕416号）.pdf",
          "downloaded": true,
          "local_path": "downloads/tiaofasi_departmental_rule/tiaofasi_departmental_rule_000040_002.pdf"
        }
      ]
    },
    {
      "serial": 39,
      "title": "中国人民银行令〔2018〕第2号（中国人民银行关于修改《金融机构大额交易和可疑交易报告管理办法》的决定）",
      "remark": "中国人民银行令〔2018〕第2号（中国人民银行关于修改《金融机构大额交易和可...",
      "documents": [
        {
          "type": "html",
          "url": "http://www.pbc.gov.cn/tiaofasi/144941/144957/3596827/index.html",
          "title": "中国人民银行令〔2018〕第2号（中国人民银行关于修改《金融机构大额交易和可疑交易报告管理办法》的决定）",
          "downloaded": true,
          "local_path": "downloads/tiaofasi_departmental_rule/tiaofasi_departmental_rule_000039_001.html"
        },
        {
          "type": "pdf",
          "url": "http://www.pbc.gov.cn/tiaofasi/144941/144957/3596827/2018080616545484338.pdf",
          "title": "中国人民银行关于修改《金融机构大额交易和可疑交易报告管理办法》的决定（中国人民银行银行令〔2018〕第2号）.pdf",
          "downloaded": true,
          "local_path": "downloads/tiaofasi_departmental_rule/tiaofasi_departmental_rule_000039_002.pdf"
        }
      ]
    },
    {
      "serial": 37,
      "title": "中国人民银行令〔2018〕第3号（中国人民银行规章制定程序与管理规定）",
      "remark": "2018-09-30",
      "documents": [
        {
          "type": "html",
          "url": "http://www.pbc.gov.cn/tiaofasi/144941/144957/3655456/index.html",
          "title": "中国人民银行令〔2018〕第3号（中国人民银行规章制定程序与管理规定）",
          "downloaded": true,
          "local_path": "downloads/tiaofasi_departmental_rule/tiaofasi_departmental_rule_000037_001.html"
        },
        {
          "type": "pdf",
          "url": "http://www.pbc.gov.cn/tiaofasi/144941/144957/3655456/2018110112490765850.pdf",
          "title": "中国人民银行令〔2018〕第3号（中国人民银行规章制定程序与管理规定）.pdf",
          "downloaded": true,
          "local_path": "downloads/tiaofasi_departmental_rule/tiaofasi_departmental_rule_000037_002.pdf"
        }
      ]
    },
    {
      "serial": 36,
      "title": "中国人民银行令〔2019〕第1号（中国人民银行关于取消企业银行账户许可有关事宜的决定）",
      "remark": "中国人民银行令〔2019〕第1号（中国人民银行关于取消企业银行账户许可有关事...",
      "documents": [
        {
          "type": "html",
          "url": "http://www.pbc.gov.cn/tiaofasi/144941/144957/3774044/index.html",
          "title": "中国人民银行令〔2019〕第1号（中国人民银行关于取消企业银行账户许可有关事宜的决定）",
          "downloaded": true,
          "local_path": "downloads/tiaofasi_departmental_rule/tiaofasi_departmental_rule_000036_001.html"
        },
        {
          "type": "pdf",
          "url": "http://www.pbc.gov.cn/tiaofasi/144941/144957/3774044/2019101811172631822.pdf",
          "title": "中国人民银行令〔2019〕第1号 （中国人民银行关于取消企业银行账户许可有关事宜的决定）.pdf",
          "downloaded": true,
          "local_path": "downloads/tiaofasi_departmental_rule/tiaofasi_departmental_rule_000036_002.pdf"
        }
      ]
    },
    {
      "serial": 35,
      "title": "中国人民银行令〔2019〕第2号 （人民币图样使用管理办法）（2019年版）",
      "remark": "2019-10-18",
      "documents": [
        {
          "type": "html",
          "url": "http://www.pbc.gov.cn/tiaofasi/144941/144957/3905164/index.html",
          "title": "中国人民银行令〔2019〕第2号 （人民币图样使用管理办法）（2019年版）",
          "downloaded": true,
          "local_path": "downloads/tiaofasi_departmental_rule/tiaofasi_departmental_rule_000035_001.html"
        },
        {
          "type": "pdf",
          "url": "http://www.pbc.gov.cn/tiaofasi/144941/144957/3905164/2019101811190737061.pdf",
          "title": "中国人民银行令〔2019〕第2号 （人民币图样使用管理办法）.pdf",
          "downloaded": true,
          "local_path": "downloads/tiaofasi_departmental_rule/tiaofasi_departmental_rule_000035_002.pdf"
        }
      ]
    },
    {
      "serial": 34,
      "title": "中国人民银行令〔2019〕第3号 （中国人民银行货币鉴别及假币收缴、鉴定管理办法）",
      "remark": "中国人民银行令〔2019〕第3号 （中国人民银行货币鉴别及假币收缴、鉴定管理...",
      "documents": [
        {
          "type": "html",
          "url": "http://www.pbc.gov.cn/tiaofasi/144941/144957/3905172/index.html",
          "title": "中国人民银行令〔2019〕第3号 （中国人民银行货币鉴别及假币收缴、鉴定管理办法）",
          "downloaded": true,
          "local_path": "downloads/tiaofasi_departmental_rule/tiaofasi_departmental_rule_000034_001.html"
        },
        {
          "type": "pdf",
          "url": "http://www.pbc.gov.cn/tiaofasi/144941/144957/3905172/2019101811261258257.pdf",
          "title": "中国人民银行令〔2019〕第3号 （中国人民银行货币鉴别及假币收缴、鉴定管理办法）.pdf",
          "downloaded": true,
          "local_path": "downloads/tiaofasi_departmental_rule/tiaofasi_departmental_rule_000034_002.pdf"
        }
      ]
    },
    {
      "serial": 33,
      "title": "中国人民银行令〔2019〕第4号（应收账款质押登记办法）",
      "remark": "2019-11-29",
      "documents": [
        {
          "type": "html",
          "url": "http://www.pbc.gov.cn/tiaofasi/144941/144957/3930640/index.html",
          "title": "中国人民银行令〔2019〕第4号（应收账款质押登记办法）",
          "downloaded": true,
          "local_path": "downloads/tiaofasi_departmental_rule/tiaofasi_departmental_rule_000033_001.html"
        },
        {
          "type": "pdf",
          "url": "http://www.pbc.gov.cn/tiaofasi/144941/144957/3930640/2019112916365924198.pdf",
          "title": "中国人民银行令〔2019〕第4号（应收账款质押登记办法）.pdf",
          "downloaded": true,
          "local_path": "downloads/tiaofasi_departmental_rule/tiaofasi_departmental_rule_000033_002.pdf"
        }
      ]
    },
    {
      "serial": 32,
      "title": "中国人民银行 国家发展和改革委员会 财政部 中国证券监督管理委员会令〔2019〕第5号（信用评级业管理暂行办法）",
      "remark": "中国人民银行 国家发展和改革委员会 财政部 中国证券监督管理委员会令〔201...",
      "documents": [
        {
          "type": "html",
          "url": "http://www.pbc.gov.cn/tiaofasi/144941/144957/3930712/index.html",
          "title": "中国人民银行 国家发展和改革委员会 财政部 中国证券监督管理委员会令〔2019〕第5号（信用评级业管理暂行办法）",
          "downloaded": true,
          "local_path": "downloads/tiaofasi_departmental_rule/tiaofasi_departmental_rule_000032_001.html"
        },
        {
          "type": "pdf",
          "url": "http://www.pbc.gov.cn/tiaofasi/144941/144957/3930712/2019112916560360082.pdf",
          "title": "中国人民银行 国家发展和改革委员会 财政部 中国证券监督管理委员会令〔2019〕第5号（信用评级业管理暂行办法）.pdf",
          "downloaded": true,
          "local_path": "downloads/tiaofasi_departmental_rule/tiaofasi_departmental_rule_000032_002.pdf"
        }
      ]
    },
    {
      "serial": 31,
      "title": "中国人民银行令〔2020〕第1号（中国人民银行行政许可实施办法）",
      "remark": "2020-04-01",
      "documents": [
        {
          "type": "html",
          "url": "http://www.pbc.gov.cn/tiaofasi/144941/144957/4001068/index.html",
          "title": "中国人民银行令〔2020〕第1号（中国人民银行行政许可实施办法）",
          "downloaded": true,
          "local_path": "downloads/tiaofasi_departmental_rule/tiaofasi_departmental_rule_000031_001.html"
        },
        {
          "type": "pdf",
          "url": "http://www.pbc.gov.cn/tiaofasi/144941/144957/4001068/2020040110545273270.pdf",
          "title": "《中国人民银行行政许可实施办法》公开征求意见及意见采纳情况.pdf",
          "downloaded": true,
          "local_path": "downloads/tiaofasi_departmental_rule/tiaofasi_departmental_rule_000031_002.pdf"
        }
      ]
    },
    {
      "serial": 56,
      "title": "中国人民银行令〔2010〕第1号（中国人民银行执法检查程序规定）",
      "remark": "2010-04-14",
      "documents": [
        {
          "type": "html",
          "url": "http://www.pbc.gov.cn/tiaofasi/144941/144957/2889727/index.html",
          "title": "中国人民银行令〔2010〕第1号（中国人民银行执法检查程序规定）",
          "downloaded": true,
          "local_path": "downloads/tiaofasi_departmental_rule/tiaofasi_departmental_rule_000056_001.html"
        },
        {
          "type": "word",
          "url": "http://www.pbc.gov.cn/eportal/fileDir/image_public/UserFiles/tiaofasi/upload/File/%E9%99%841%EF%BC%9A%E6%89%A7%E6%B3%95%E6%A3%80%E6%9F%A5%E7%AB%8B%E9%A1%B9%E5%AE%A1%E6%89%B9%E8%A1%A8.doc",
          "title": "附1：执法检查立项审批表.doc",
          "downloaded": true,
          "local_path": "downloads/tiaofasi_departmental_rule/tiaofasi_departmental_rule_000056_002.doc"
        },
        {
          "type": "word",
          "url": "http://www.pbc.gov.cn/eportal/fileDir/image_public/UserFiles/tiaofasi/upload/File/%E9%99%842%EF%BC%9A%E6%89%A7%E6%B3%95%E6%A3%80%E6%9F%A5%E9%80%9A%E7%9F%A5%E4%B9%A6.doc",
          "title": "附2：执法检查通知书.doc",
          "downloaded": true,
          "local_path": "downloads/tiaofasi_departmental_rule/tiaofasi_departmental_rule_000056_003.doc"
        },
        {
          "type": "word",
          "url": "http://www.pbc.gov.cn/eportal/fileDir/image_public/UserFiles/tiaofasi/upload/File/%E9%99%843%EF%BC%9A%E6%89%A7%E6%B3%95%E6%A3%80%E6%9F%A5%E8%BF%9B%E5%9C%BA%E8%AE%B0%E5%BD%95.doc",
          "title": "附3：执法检查进场记录.doc",
          "downloaded": true,
          "local_path": "downloads/tiaofasi_departmental_rule/tiaofasi_departmental_rule_000056_004.doc"
        },
        {
          "type": "word",
          "url": "http://www.pbc.gov.cn/eportal/fileDir/image_public/UserFiles/tiaofasi/upload/File/%E9%99%844%EF%BC%9A%E6%89%A7%E6%B3%95%E6%A3%80%E6%9F%A5%E4%BC%9A%E8%B0%88%E7%BA%AA%E8%A6%81.doc",
          "title": "附4：执法检查会谈纪要.doc",
          "downloaded": true,
          "local_path": "downloads/tiaofasi_departmental_rule/tiaofasi_departmental_rule_000056_005.doc"
        },
        {
          "type": "word",
          "url": "http://www.pbc.gov.cn/eportal/fileDir/image_public/UserFiles/tiaofasi/upload/File/%E9%99%845%EF%BC%9A%E6%89%A7%E6%B3%95%E6%A3%80%E6%9F%A5%E8%B0%83%E9%98%85%E8%B5%84%E6%96%99%E6%B8%85%E5%8D%95.doc",
          "title": "附5：执法检查调阅资料清单.doc",
          "downloaded": true,
          "local_path": "downloads/tiaofasi_departmental_rule/tiaofasi_departmental_rule_000056_006.doc"
        },
        {
          "type": "word",
          "url": "http://www.pbc.gov.cn/eportal/fileDir/image_public/UserFiles/tiaofasi/upload/File/%E9%99%846%EF%BC%9A%E6%89%A7%E6%B3%95%E6%A3%80%E6%9F%A5%E8%AF%A2%E9%97%AE%E7%AC%94%E5%BD%95.doc",
          "title": "附6：执法检查询问笔录.doc",
          "downloaded": true,
          "local_path": "downloads/tiaofasi_departmental_rule/tiaofasi_departmental_rule_000056_007.doc"
        },
        {
          "type": "word",
          "url": "http://www.pbc.gov.cn/eportal/fileDir/image_public/UserFiles/tiaofasi/upload/File/%E9%99%847%EF%BC%9A%E6%89%A7%E6%B3%95%E6%A3%80%E6%9F%A5%E8%AF%81%E6%8D%AE%E7%99%BB%E8%AE%B0%E4%BF%9D%E5%AD%98%E9%80%9A%E7%9F%A5%E4%B9%A6.doc",
          "title": "附7：执法检查证据登记保存通知书.doc",
          "downloaded": true,
          "local_path": "downloads/tiaofasi_departmental_rule/tiaofasi_departmental_rule_000056_008.doc"
        },
        {
          "type": "word",
          "url": "http://www.pbc.gov.cn/eportal/fileDir/image_public/UserFiles/tiaofasi/upload/File/%E9%99%848%EF%BC%9A%E6%89%A7%E6%B3%95%E6%A3%80%E6%9F%A5%E5%B7%A5%E4%BD%9C%E5%BA%95%E7%A8%BF.doc",
          "title": "附8：执法检查工作底稿.doc",
          "downloaded": true,
          "local_path": "downloads/tiaofasi_departmental_rule/tiaofasi_departmental_rule_000056_009.doc"
        },
        {
          "type": "word",
          "url": "http://www.pbc.gov.cn/eportal/fileDir/image_public/UserFiles/tiaofasi/upload/File/%E9%99%849%EF%BC%9A%E6%89%A7%E6%B3%95%E6%A3%80%E6%9F%A5%E4%BA%8B%E5%AE%9E%E8%AE%A4%E5%AE%9A%E4%B9%A6.doc",
          "title": "附9：执法检查事实认定书.doc",
          "downloaded": true,
          "local_path": "downloads/tiaofasi_departmental_rule/tiaofasi_departmental_rule_000056_010.doc"
        }
      ]
    },
    {
      "serial": 24,
      "title": "中国人民银行令〔2021〕第3号（金融机构反洗钱和反恐怖融资监督管理办法）",
      "remark": "2021-04-16",
      "documents": [
        {
          "type": "html",
          "url": "http://www.pbc.gov.cn/tiaofasi/144941/144957/4232619/index.html",
          "title": "中国人民银行令〔2021〕第3号（金融机构反洗钱和反恐怖融资监督管理办法）",
          "downloaded": true,
          "local_path": "downloads/tiaofasi_departmental_rule/tiaofasi_departmental_rule_000024_001.html"
        },
        {
          "type": "word",
          "url": "http://www.pbc.gov.cn/tiaofasi/144941/144957/4232619/2021041616361284745.doc",
          "title": "附件.doc",
          "downloaded": true,
          "local_path": "downloads/tiaofasi_departmental_rule/tiaofasi_departmental_rule_000024_002.doc"
        }
      ]
    },
    {
      "serial": 106,
      "title": "商业银行设立同城营业网点管理办法",
      "remark": "2002-03-11",
      "documents": [
        {
          "type": "html",
          "url": "http://www.pbc.gov.cn/tiaofasi/144941/144957/2817058/index.html",
          "title": "商业银行设立同城营业网点管理办法",
          "downloaded": true,
          "local_path": "downloads/tiaofasi_departmental_rule/tiaofasi_departmental_rule_000106_001.html"
        }
      ]
    },
    {
      "serial": 105,
      "title": "信托投资公司管理办法",
      "remark": "2002-05-24",
      "documents": [
        {
          "type": "html",
          "url": "http://www.pbc.gov.cn/tiaofasi/144941/144957/2885660/index.html",
          "title": "信托投资公司管理办法",
          "downloaded": true,
          "local_path": "downloads/tiaofasi_departmental_rule/tiaofasi_departmental_rule_000105_001.html"
        }
      ]
    },
    {
      "serial": 104,
      "title": "商业银行信息披露暂行办法",
      "remark": "2002-05-28",
      "documents": [
        {
          "type": "html",
          "url": "http://www.pbc.gov.cn/tiaofasi/144941/144957/2884009/index.html",
          "title": "商业银行信息披露暂行办法",
          "downloaded": true,
          "local_path": "downloads/tiaofasi_departmental_rule/tiaofasi_departmental_rule_000104_001.html"
        }
      ]
    },
    {
      "serial": 103,
      "title": "信托投资公司资金信托管理暂行办法",
      "remark": "2002-06-25",
      "documents": [
        {
          "type": "html",
          "url": "http://www.pbc.gov.cn/tiaofasi/144941/144957/2892722/index.html",
          "title": "信托投资公司资金信托管理暂行办法",
          "downloaded": true,
          "local_path": "downloads/tiaofasi_departmental_rule/tiaofasi_departmental_rule_000103_001.html"
        }
      ]
    },
    {
      "serial": 102,
      "title": "外资金融机构驻华代表机构管理办法",
      "remark": "2002-06-25",
      "documents": [
        {
          "type": "html",
          "url": "http://www.pbc.gov.cn/tiaofasi/144941/144957/2817065/index.html",
          "title": "外资金融机构驻华代表机构管理办法",
          "downloaded": true,
          "local_path": "downloads/tiaofasi_departmental_rule/tiaofasi_departmental_rule_000102_001.html"
        }
      ]
    },
    {
      "serial": 99,
      "title": "人民币大额和可疑支付交易报告管理办法",
      "remark": "2003-01-14",
      "documents": [
        {
          "type": "html",
          "url": "http://www.pbc.gov.cn/tiaofasi/144941/144957/2817349/index.html",
          "title": "人民币大额和可疑支付交易报告管理办法",
          "downloaded": true,
          "local_path": "downloads/tiaofasi_departmental_rule/tiaofasi_departmental_rule_000099_001.html"
        }
      ]
    },
    {
      "serial": 98,
      "title": "金融机构大额和可疑外汇资金交易报告管理办法",
      "remark": "2003-01-15",
      "documents": [
        {
          "type": "html",
          "url": "http://www.pbc.gov.cn/tiaofasi/144941/144957/2897466/index.html",
          "title": "金融机构大额和可疑外汇资金交易报告管理办法",
          "downloaded": true,
          "local_path": "downloads/tiaofasi_departmental_rule/tiaofasi_departmental_rule_000098_001.html"
        }
      ]
    },
    {
      "serial": 97,
      "title": "人民币银行结算账户管理办法",
      "remark": "2003-04-10",
      "documents": [
        {
          "type": "html",
          "url": "http://www.pbc.gov.cn/tiaofasi/144941/144957/2817125/index.html",
          "title": "人民币银行结算账户管理办法",
          "downloaded": true,
          "local_path": "downloads/tiaofasi_departmental_rule/tiaofasi_departmental_rule_000097_001.html"
        }
      ]
    },
    {
      "serial": 95,
      "title": "中国人民银行假币收缴、鉴定管理办法",
      "remark": "2003-04-15",
      "documents": [
        {
          "type": "html",
          "url": "http://www.pbc.gov.cn/tiaofasi/144941/144957/2817346/index.html",
          "title": "中国人民银行假币收缴、鉴定管理办法",
          "downloaded": true,
          "local_path": "downloads/tiaofasi_departmental_rule/tiaofasi_departmental_rule_000095_001.html"
        }
      ]
    },
    {
      "serial": 94,
      "title": "外币代兑机构管理暂行办法",
      "remark": "2003-10-08",
      "documents": [
        {
          "type": "html",
          "url": "http://www.pbc.gov.cn/tiaofasi/144941/144957/2877537/index.html",
          "title": "外币代兑机构管理暂行办法",
          "downloaded": true,
          "local_path": "downloads/tiaofasi_departmental_rule/tiaofasi_departmental_rule_000094_001.html"
        }
      ]
    },
    {
      "serial": 93,
      "title": "中国人民银行残缺污损人民币兑换办法",
      "remark": "2003-12-24",
      "documents": [
        {
          "type": "html",
          "url": "http://www.pbc.gov.cn/tiaofasi/144941/144957/2817130/index.html",
          "title": "中国人民银行残缺污损人民币兑换办法",
          "downloaded": true,
          "local_path": "downloads/tiaofasi_departmental_rule/tiaofasi_departmental_rule_000093_001.html"
        }
      ]
    },
    {
      "serial": 91,
      "title": "全国银行间债券市场债券买断式回购业务管理规定",
      "remark": "2004-04-12",
      "documents": [
        {
          "type": "html",
          "url": "http://www.pbc.gov.cn/tiaofasi/144941/144957/2890765/index.html",
          "title": "全国银行间债券市场债券买断式回购业务管理规定",
          "downloaded": true,
          "local_path": "downloads/tiaofasi_departmental_rule/tiaofasi_departmental_rule_000091_001.html"
        }
      ]
    },
    {
      "serial": 89,
      "title": "中国人民银行令〔2004〕第3号（中国人民银行行政许可法实施办法）",
      "remark": "2004-09-13",
      "documents": [
        {
          "type": "html",
          "url": "http://www.pbc.gov.cn/tiaofasi/144941/144957/2877541/index.html",
          "title": "中国人民银行令〔2004〕第3号（中国人民银行行政许可法实施办法）",
          "downloaded": true,
          "local_path": "downloads/tiaofasi_departmental_rule/tiaofasi_departmental_rule_000089_001.html"
        }
      ]
    },
    {
      "serial": 88,
      "title": "中国人民银行令〔2005〕第1号（全国银行间债券市场金融债券发行管理办法）",
      "remark": "2005-04-27",
      "documents": [
        {
          "type": "html",
          "url": "http://www.pbc.gov.cn/tiaofasi/144941/144957/2899481/index.html",
          "title": "中国人民银行令〔2005〕第1号（全国银行间债券市场金融债券发行管理办法）",
          "downloaded": true,
          "local_path": "downloads/tiaofasi_departmental_rule/tiaofasi_departmental_rule_000088_001.html"
        }
      ]
    },
    {
      "serial": 87,
      "title": "短期融资券管理办法",
      "remark": "2005-05-24",
      "documents": [
        {
          "type": "html",
          "url": "http://www.pbc.gov.cn/tiaofasi/144941/144957/2817096/index.html",
          "title": "短期融资券管理办法",
          "downloaded": true,
          "local_path": "downloads/tiaofasi_departmental_rule/tiaofasi_departmental_rule_000087_001.html"
        }
      ]
    },
    {
      "serial": 78,
      "title": "金融机构高级管理人员任职资格管理办法",
      "remark": "2000-12-01",
      "documents": [
        {
          "type": "html",
          "url": "http://www.pbc.gov.cn/tiaofasi/144941/144957/2887785/index.html",
          "title": "金融机构高级管理人员任职资格管理办法",
          "downloaded": true,
          "local_path": "downloads/tiaofasi_departmental_rule/tiaofasi_departmental_rule_000078_001.html"
        }
      ]
    },
    {
      "serial": 77,
      "title": "企业集团财务公司管理办法",
      "remark": "2000-12-01",
      "documents": [
        {
          "type": "html",
          "url": "http://www.pbc.gov.cn/tiaofasi/144941/144957/2875216/index.html",
          "title": "企业集团财务公司管理办法",
          "downloaded": true,
          "local_path": "downloads/tiaofasi_departmental_rule/tiaofasi_departmental_rule_000077_001.html"
        }
      ]
    },
    {
      "serial": 76,
      "title": "全国银行间债券市场债券交易管理办法",
      "remark": "2000-12-01",
      "documents": [
        {
          "type": "html",
          "url": "http://www.pbc.gov.cn/tiaofasi/144941/144957/2817076/index.html",
          "title": "全国银行间债券市场债券交易管理办法",
          "downloaded": true,
          "local_path": "downloads/tiaofasi_departmental_rule/tiaofasi_departmental_rule_000076_001.html"
        }
      ]
    },
    {
      "serial": 75,
      "title": "金融租赁公司管理办法",
      "remark": "2000-12-01",
      "documents": [
        {
          "type": "html",
          "url": "http://www.pbc.gov.cn/tiaofasi/144941/144957/2817307/index.html",
          "title": "金融租赁公司管理办法",
          "downloaded": true,
          "local_path": "downloads/tiaofasi_departmental_rule/tiaofasi_departmental_rule_000075_001.html"
        }
      ]
    },
    {
      "serial": 73,
      "title": "商业银行、信用社代理国库业务管理办法",
      "remark": "2001-02-01",
      "documents": [
        {
          "type": "html",
          "url": "http://www.pbc.gov.cn/tiaofasi/144941/144957/2817313/index.html",
          "title": "商业银行、信用社代理国库业务管理办法",
          "downloaded": true,
          "local_path": "downloads/tiaofasi_departmental_rule/tiaofasi_departmental_rule_000073_001.html"
        }
      ]
    },
    {
      "serial": 72,
      "title": "中国人民银行行政复议办法",
      "remark": "2001-02-01",
      "documents": [
        {
          "type": "html",
          "url": "http://www.pbc.gov.cn/tiaofasi/144941/144957/2873574/index.html",
          "title": "中国人民银行行政复议办法",
          "downloaded": true,
          "local_path": "downloads/tiaofasi_departmental_rule/tiaofasi_departmental_rule_000072_001.html"
        }
      ]
    },
    {
      "serial": 71,
      "title": "中国人民银行行政处罚程序规定",
      "remark": "2001-02-01",
      "documents": [
        {
          "type": "html",
          "url": "http://www.pbc.gov.cn/tiaofasi/144941/144957/2875222/index.html",
          "title": "中国人民银行行政处罚程序规定",
          "downloaded": true,
          "local_path": "downloads/tiaofasi_departmental_rule/tiaofasi_departmental_rule_000071_001.html"
        }
      ]
    },
    {
      "serial": 68,
      "title": "商业银行中间业务暂行规定",
      "remark": "2001-07-01",
      "documents": [
        {
          "type": "html",
          "url": "http://www.pbc.gov.cn/tiaofasi/144941/144957/2894344/index.html",
          "title": "商业银行中间业务暂行规定",
          "downloaded": true,
          "local_path": "downloads/tiaofasi_departmental_rule/tiaofasi_departmental_rule_000068_001.html"
        }
      ]
    },
    {
      "serial": 67,
      "title": "商业银行柜台记账式国债交易管理办法",
      "remark": "2002-02-25",
      "documents": [
        {
          "type": "html",
          "url": "http://www.pbc.gov.cn/tiaofasi/144941/144957/2897463/index.html",
          "title": "商业银行柜台记账式国债交易管理办法",
          "downloaded": true,
          "local_path": "downloads/tiaofasi_departmental_rule/tiaofasi_departmental_rule_000067_001.html"
        }
      ]
    },
    {
      "serial": 66,
      "title": "中国人民银行突发事件应急预案管理办法",
      "remark": "2005-08-05",
      "documents": [
        {
          "type": "html",
          "url": "http://www.pbc.gov.cn/tiaofasi/144941/144957/2887789/index.html",
          "title": "中国人民银行突发事件应急预案管理办法",
          "downloaded": true,
          "local_path": "downloads/tiaofasi_departmental_rule/tiaofasi_departmental_rule_000066_001.html"
        }
      ]
    },
    {
      "serial": 65,
      "title": "中国人民银行令〔2005〕第3号（个人信用信息基础数据库管理暂行办法）",
      "remark": "2005-08-18",
      "documents": [
        {
          "type": "html",
          "url": "http://www.pbc.gov.cn/tiaofasi/144941/144957/2817105/index.html",
          "title": "中国人民银行令〔2005〕第3号（个人信用信息基础数据库管理暂行办法）",
          "downloaded": true,
          "local_path": "downloads/tiaofasi_departmental_rule/tiaofasi_departmental_rule_000065_001.html"
        }
      ]
    },
    {
      "serial": 64,
      "title": "国债承销团成员审批办法",
      "remark": "2006-07-21",
      "documents": [
        {
          "type": "html",
          "url": "http://www.pbc.gov.cn/tiaofasi/144941/144957/2817233/index.html",
          "title": "国债承销团成员审批办法",
          "downloaded": true,
          "local_path": "downloads/tiaofasi_departmental_rule/tiaofasi_departmental_rule_000064_001.html"
        }
      ]
    },
    {
      "serial": 63,
      "title": "中国人民银行令〔2006〕第1号（金融机构反洗钱规定）",
      "remark": "2006-11-14",
      "documents": [
        {
          "type": "html",
          "url": "http://www.pbc.gov.cn/tiaofasi/144941/144957/2817499/index.html",
          "title": "中国人民银行令〔2006〕第1号（金融机构反洗钱规定）",
          "downloaded": true,
          "local_path": "downloads/tiaofasi_departmental_rule/tiaofasi_departmental_rule_000063_001.html"
        }
      ]
    },
    {
      "serial": 60,
      "title": "中国人民银行令〔2007〕第3号（同业拆借管理办法）",
      "remark": "2007-07-03",
      "documents": [
        {
          "type": "html",
          "url": "http://www.pbc.gov.cn/tiaofasi/144941/144957/2881277/index.html",
          "title": "中国人民银行令〔2007〕第3号（同业拆借管理办法）",
          "downloaded": true,
          "local_path": "downloads/tiaofasi_departmental_rule/tiaofasi_departmental_rule_000060_001.html"
        }
      ]
    },
    {
      "serial": 55,
      "title": "中国人民银行令〔2013〕第1号（征信机构管理办法）",
      "remark": "2013-11-15",
      "documents": [
        {
          "type": "html",
          "url": "http://www.pbc.gov.cn/tiaofasi/144941/144957/2898843/index.html",
          "title": "中国人民银行令〔2013〕第1号（征信机构管理办法）",
          "downloaded": true,
          "local_path": "downloads/tiaofasi_departmental_rule/tiaofasi_departmental_rule_000055_001.html"
        }
      ]
    },
    {
      "serial": 54,
      "title": "中国人民银行 公安部 国家安全部令〔2014〕第1号（涉及恐怖活动资产冻结管理办法）",
      "remark": "中国人民银行 公安部 国家安全部令〔2014〕第1号（涉及恐怖活动资产冻结管理...",
      "documents": [
        {
          "type": "html",
          "url": "http://www.pbc.gov.cn/tiaofasi/144941/144957/2805014/index.html",
          "title": "中国人民银行 公安部 国家安全部令〔2014〕第1号（涉及恐怖活动资产冻结管理办法）",
          "downloaded": true,
          "local_path": "downloads/tiaofasi_departmental_rule/tiaofasi_departmental_rule_000054_001.html"
        }
      ]
    },
    {
      "serial": 53,
      "title": "中国人民银行令〔2014〕第2号（银行办理结售汇业务管理办法）",
      "remark": "2014-06-22",
      "documents": [
        {
          "type": "html",
          "url": "http://www.pbc.gov.cn/tiaofasi/144941/144957/2807110/index.html",
          "title": "中国人民银行令〔2014〕第2号（银行办理结售汇业务管理办法）",
          "downloaded": true,
          "local_path": "downloads/tiaofasi_departmental_rule/tiaofasi_departmental_rule_000053_001.html"
        }
      ]
    },
    {
      "serial": 51,
      "title": "中国人民银行 中国银行业监督管理委员会令〔2016〕第2号（银行卡清算机构管理办法）",
      "remark": "中国人民银行 中国银行业监督管理委员会令〔2016〕第2号（银行卡清算机构管...",
      "documents": [
        {
          "type": "html",
          "url": "http://www.pbc.gov.cn/tiaofasi/144941/144957/3078009/index.html",
          "title": "中国人民银行 中国银行业监督管理委员会令〔2016〕第2号（银行卡清算机构管理办法）",
          "downloaded": true,
          "local_path": "downloads/tiaofasi_departmental_rule/tiaofasi_departmental_rule_000051_001.html"
        }
      ]
    },
    {
      "serial": 30,
      "title": "中国人民银行 海关总署令〔2020〕第3号（修改《黄金及黄金制品进出口管理办法》）",
      "remark": "中国人民银行 海关总署令〔2020〕第3号（修改《黄金及黄金制品进出口管理办...",
      "documents": [
        {
          "type": "html",
          "url": "http://www.pbc.gov.cn/tiaofasi/144941/144957/4032405/index.html",
          "title": "中国人民银行 海关总署令〔2020〕第3号（修改《黄金及黄金制品进出口管理办法》）",
          "downloaded": true,
          "local_path": "downloads/tiaofasi_departmental_rule/tiaofasi_departmental_rule_000030_001.html"
        }
      ]
    },
    {
      "serial": 29,
      "title": "中国人民银行令〔2020〕第2号（关于修改《教育储蓄管理办法》等规章的决定）",
      "remark": "2020-06-02",
      "documents": [
        {
          "type": "html",
          "url": "http://www.pbc.gov.cn/tiaofasi/144941/144957/4032025/index.html",
          "title": "中国人民银行令〔2020〕第2号（关于修改《教育储蓄管理办法》等规章的决定）",
          "downloaded": true,
          "local_path": "downloads/tiaofasi_departmental_rule/tiaofasi_departmental_rule_000029_001.html"
        }
      ]
    },
    {
      "serial": 28,
      "title": "中国人民银行令〔2020〕第4号（金融控股公司监督管理试行办法）",
      "remark": "2020-09-13",
      "documents": [
        {
          "type": "html",
          "url": "http://www.pbc.gov.cn/tiaofasi/144941/144957/4093006/index.html",
          "title": "中国人民银行令〔2020〕第4号（金融控股公司监督管理试行办法）",
          "downloaded": true,
          "local_path": "downloads/tiaofasi_departmental_rule/tiaofasi_departmental_rule_000028_001.html"
        }
      ]
    },
    {
      "serial": 27,
      "title": "中国人民银行令〔2020〕第5号（中国人民银行金融消费者权益保护实施办法）",
      "remark": "2020-09-18",
      "documents": [
        {
          "type": "html",
          "url": "http://www.pbc.gov.cn/tiaofasi/144941/144957/4099060/index.html",
          "title": "中国人民银行令〔2020〕第5号（中国人民银行金融消费者权益保护实施办法）",
          "downloaded": true,
          "local_path": "downloads/tiaofasi_departmental_rule/tiaofasi_departmental_rule_000027_001.html"
        }
      ]
    },
    {
      "serial": 26,
      "title": "中国人民银行令〔2021〕第1号（非银行支付机构客户备付金存管办法）",
      "remark": "2021-01-22",
      "documents": [
        {
          "type": "html",
          "url": "http://www.pbc.gov.cn/tiaofasi/144941/144957/4168458/index.html",
          "title": "中国人民银行令〔2021〕第1号（非银行支付机构客户备付金存管办法）",
          "downloaded": true,
          "local_path": "downloads/tiaofasi_departmental_rule/tiaofasi_departmental_rule_000026_001.html"
        }
      ]
    },
    {
      "serial": 25,
      "title": "中国人民银行令〔2021〕第2号（金融控股公司董事、监事、高级管理人员任职备案管理暂行规定）",
      "remark": "中国人民银行令〔2021〕第2号（金融控股公司董事、监事、高级管理人员任职备...",
      "documents": [
        {
          "type": "html",
          "url": "http://www.pbc.gov.cn/tiaofasi/144941/144957/4223180/index.html",
          "title": "中国人民银行令〔2021〕第2号（金融控股公司董事、监事、高级管理人员任职备案管理暂行规定）",
          "downloaded": true,
          "local_path": "downloads/tiaofasi_departmental_rule/tiaofasi_departmental_rule_000025_001.html"
        }
      ]
    },
    {
      "serial": 23,
      "title": "中国人民银行令〔2021〕第4号（征信业务管理办法）",
      "remark": "2021-09-30",
      "documents": [
        {
          "type": "html",
          "url": "http://www.pbc.gov.cn/tiaofasi/144941/144957/4354378/index.html",
          "title": "中国人民银行令〔2021〕第4号（征信业务管理办法）",
          "downloaded": true,
          "local_path": "downloads/tiaofasi_departmental_rule/tiaofasi_departmental_rule_000023_001.html"
        }
      ]
    },
    {
      "serial": 22,
      "title": "中国人民银行 中国银行保险监督管理委员会令〔2021〕第5号（系统重要性银行附加监管规定（试行））",
      "remark": "中国人民银行 中国银行保险监督管理委员会令〔2021〕第5号（系统重要性银行...",
      "documents": [
        {
          "type": "html",
          "url": "http://www.pbc.gov.cn/tiaofasi/144941/144957/4361118/index.html",
          "title": "中国人民银行 中国银行保险监督管理委员会令〔2021〕第5号（系统重要性银行附加监管规定（试行））",
          "downloaded": true,
          "local_path": "downloads/tiaofasi_departmental_rule/tiaofasi_departmental_rule_000022_001.html"
        }
      ]
    },
    {
      "serial": 21,
      "title": "中国人民银行 中国银行保险监督管理委员会 财政部令〔2021〕第6号（全球系统重要性银行总损失吸收能力管理办法）",
      "remark": "中国人民银行 中国银行保险监督管理委员会 财政部令〔2021〕第6号（全球系统...",
      "documents": [
        {
          "type": "html",
          "url": "http://www.pbc.gov.cn/tiaofasi/144941/144957/4373500/index.html",
          "title": "中国人民银行 中国银行保险监督管理委员会 财政部令〔2021〕第6号（全球系统重要性银行总损失吸收能力管理办法）",
          "downloaded": true,
          "local_path": "downloads/tiaofasi_departmental_rule/tiaofasi_departmental_rule_000021_001.html"
        }
      ]
    },
    {
      "serial": 20,
      "title": "中国人民银行令〔2021〕第7号（动产和权利担保统一登记办法）",
      "remark": "2021-12-30",
      "documents": [
        {
          "type": "html",
          "url": "http://www.pbc.gov.cn/tiaofasi/144941/144957/4435867/index.html",
          "title": "中国人民银行令〔2021〕第7号（动产和权利担保统一登记办法）",
          "downloaded": true,
          "local_path": "downloads/tiaofasi_departmental_rule/tiaofasi_departmental_rule_000020_001.html"
        }
      ]
    },
    {
      "serial": 19,
      "title": "中国人民银行 中国银行保险监督管理委员会 中国证券监督管理委员会令〔2022〕第1号（金融机构客户尽职调查和客户身份资料及交易记录保存管理办法）",
      "remark": "中国人民银行 中国银行保险监督管理委员会 中国证券监督管理委员会令〔2022...",
      "documents": [
        {
          "type": "html",
          "url": "http://www.pbc.gov.cn/tiaofasi/144941/144957/4460304/index.html",
          "title": "中国人民银行 中国银行保险监督管理委员会 中国证券监督管理委员会令〔2022〕第1号（金融机构客户尽职调查和客户身份资料及交易记录保存管理办法）",
          "downloaded": true,
          "local_path": "downloads/tiaofasi_departmental_rule/tiaofasi_departmental_rule_000019_001.html"
        }
      ]
    },
    {
      "serial": 18,
      "title": "中国人民银行令〔2022〕第2号（中国人民银行执法检查程序规定）",
      "remark": "2022-04-19",
      "documents": [
        {
          "type": "html",
          "url": "http://www.pbc.gov.cn/tiaofasi/144941/144957/4532504/index.html",
          "title": "中国人民银行令〔2022〕第2号（中国人民银行执法检查程序规定）",
          "downloaded": true,
          "local_path": "downloads/tiaofasi_departmental_rule/tiaofasi_departmental_rule_000018_001.html"
        }
      ]
    },
    {
      "serial": 17,
      "title": "中国人民银行令〔2022〕第3号（中国人民银行行政处罚程序规定）",
      "remark": "2022-04-19",
      "documents": [
        {
          "type": "html",
          "url": "http://www.pbc.gov.cn/tiaofasi/144941/144957/4532497/index.html",
          "title": "中国人民银行令〔2022〕第3号（中国人民银行行政处罚程序规定）",
          "downloaded": true,
          "local_path": "downloads/tiaofasi_departmental_rule/tiaofasi_departmental_rule_000017_001.html"
        }
      ]
    },
    {
      "serial": 16,
      "title": "中国人民银行 中国银行保险监督管理委员会令〔2022〕第4号(商业汇票承兑、贴现与再贴现管理办法)",
      "remark": "中国人民银行 中国银行保险监督管理委员会令〔2022〕第4号(商业汇票承兑、贴...",
      "documents": [
        {
          "type": "html",
          "url": "http://www.pbc.gov.cn/tiaofasi/144941/144957/4715325/index.html",
          "title": "中国人民银行 中国银行保险监督管理委员会令〔2022〕第4号(商业汇票承兑、贴现与再贴现管理办法)",
          "downloaded": true,
          "local_path": "downloads/tiaofasi_departmental_rule/tiaofasi_departmental_rule_000016_001.html"
        }
      ]
    },
    {
      "serial": 15,
      "title": "中国人民银行令〔2023〕第1号（金融控股公司关联交易管理办法）",
      "remark": "2023-02-09",
      "documents": [
        {
          "type": "html",
          "url": "http://www.pbc.gov.cn/tiaofasi/144941/144957/4789611/index.html",
          "title": "中国人民银行令〔2023〕第1号（金融控股公司关联交易管理办法）",
          "downloaded": true,
          "local_path": "downloads/tiaofasi_departmental_rule/tiaofasi_departmental_rule_000015_001.html"
        }
      ]
    },
    {
      "serial": 13,
      "title": "中国人民银行令〔2024〕第1号（中国人民银行关于修改《支付结算办法》的决定）",
      "remark": "中国人民银行令〔2024〕第1号（中国人民银行关于修改《支付结算办法》的决定...",
      "documents": [
        {
          "type": "html",
          "url": "http://www.pbc.gov.cn/tiaofasi/144941/144957/5238370/index.html",
          "title": "中国人民银行令〔2024〕第1号（中国人民银行关于修改《支付结算办法》的决定）",
          "downloaded": true,
          "local_path": "downloads/tiaofasi_departmental_rule/tiaofasi_departmental_rule_000013_001.html"
        }
      ]
    },
    {
      "serial": 11,
      "title": "中国人民银行 国家市场监督管理总局令〔2024〕第3号（受益所有人信息管理办法）",
      "remark": "中国人民银行 国家市场监督管理总局令〔2024〕第3号（受益所有人信息管理办...",
      "documents": [
        {
          "type": "html",
          "url": "http://www.pbc.gov.cn/tiaofasi/144941/144957/5342579/index.html",
          "title": "中国人民银行 国家市场监督管理总局令〔2024〕第3号（受益所有人信息管理办法）",
          "downloaded": true,
          "local_path": "downloads/tiaofasi_departmental_rule/tiaofasi_departmental_rule_000011_001.html"
        }
      ]
    },
    {
      "serial": 10,
      "title": "中国人民银行令〔2024〕第4号（非银行支付机构监督管理条例实施细则）",
      "remark": "2024-07-26",
      "documents": [
        {
          "type": "html",
          "url": "http://www.pbc.gov.cn/tiaofasi/144941/144957/5414094/index.html",
          "title": "中国人民银行令〔2024〕第4号（非银行支付机构监督管理条例实施细则）",
          "downloaded": true,
          "local_path": "downloads/tiaofasi_departmental_rule/tiaofasi_departmental_rule_000010_001.html"
        }
      ]
    },
    {
      "serial": 9,
      "title": "中国人民银行令〔2024〕第5号（中国人民银行关于修改部分规章的决定）",
      "remark": "2024-11-01",
      "documents": [
        {
          "type": "html",
          "url": "http://www.pbc.gov.cn/tiaofasi/144941/144957/5494933/index.html",
          "title": "中国人民银行令〔2024〕第5号（中国人民银行关于修改部分规章的决定）",
          "downloaded": true,
          "local_path": "downloads/tiaofasi_departmental_rule/tiaofasi_departmental_rule_000009_001.html"
        }
      ]
    },
    {
      "serial": 8,
      "title": "中国人民银行令〔2024〕第6号(中国人民银行行政处罚裁量基准适用规定)",
      "remark": "2024-11-29",
      "documents": [
        {
          "type": "html",
          "url": "http://www.pbc.gov.cn/tiaofasi/144941/144957/5522282/index.html",
          "title": "中国人民银行令〔2024〕第6号(中国人民银行行政处罚裁量基准适用规定)",
          "downloaded": true,
          "local_path": "downloads/tiaofasi_departmental_rule/tiaofasi_departmental_rule_000008_001.html"
        }
      ]
    },
    {
      "serial": 6,
      "title": "中国人民银行 国家金融监督管理总局令〔2025〕第2号（银行卡清算机构管理办法）",
      "remark": "中国人民银行 国家金融监督管理总局令〔2025〕第2号（银行卡清算机构管理办...",
      "documents": [
        {
          "type": "html",
          "url": "http://www.pbc.gov.cn/tiaofasi/144941/144957/5695473/index.html",
          "title": "中国人民银行 国家金融监督管理总局令〔2025〕第2号（银行卡清算机构管理办法）",
          "downloaded": true,
          "local_path": "downloads/tiaofasi_departmental_rule/tiaofasi_departmental_rule_000006_001.html"
        }
      ]
    },
    {
      "serial": 5,
      "title": "中国人民银行令〔2025〕第3号（中国人民银行业务领域数据安全管理办法）",
      "remark": "2025-05-09",
      "documents": [
        {
          "type": "html",
          "url": "http://www.pbc.gov.cn/tiaofasi/144941/144957/5702602/index.html",
          "title": "中国人民银行令〔2025〕第3号（中国人民银行业务领域数据安全管理办法）",
          "downloaded": true,
          "local_path": "downloads/tiaofasi_departmental_rule/tiaofasi_departmental_rule_000005_001.html"
        }
      ]
    },
    {
      "serial": 4,
      "title": "中国人民银行令〔2025〕第4号(中国人民银行业务领域网络安全事件报告管理办法)",
      "remark": "中国人民银行令〔2025〕第4号(中国人民银行业务领域网络安全事件报告管理办...",
      "documents": [
        {
          "type": "html",
          "url": "http://www.pbc.gov.cn/tiaofasi/144941/144957/5728831/index.html",
          "title": "中国人民银行令〔2025〕第4号(中国人民银行业务领域网络安全事件报告管理办法)",
          "downloaded": true,
          "local_path": "downloads/tiaofasi_departmental_rule/tiaofasi_departmental_rule_000004_001.html"
        }
      ]
    },
    {
      "serial": 1,
      "title": "中国人民银行 中国证监会令〔2025〕第7号（金融基础设施监督管理办法）",
      "remark": "2025-08-01",
      "documents": [
        {
          "type": "html",
          "url": "http://www.pbc.gov.cn/tiaofasi/144941/144957/5798411/index.html",
          "title": "中国人民银行 中国证监会令〔2025〕第7号（金融基础设施监督管理办法）",
          "downloaded": true,
          "local_path": "downloads/tiaofasi_departmental_rule/tiaofasi_departmental_rule_000001_001.html"
        }
      ]
    },
    {
      "serial": 101,
      "title": "商业银行内部控制指引",
      "remark": "2002-09-18",
      "documents": [
        {
          "type": "html",
          "url": "http://www.pbc.gov.cn/tiaofasi/144941/144957/2817325/index.html",
          "title": "商业银行内部控制指引",
          "downloaded": true,
          "local_path": "downloads/tiaofasi_departmental_rule/tiaofasi_departmental_rule_000101_001.html"
        }
      ]
    },
    {
      "serial": 107,
      "title": "中国人民银行令〔2025〕第10号（中国人民银行关于修改和废止部分规章的决定）",
      "remark": "中国人民银行令〔2025〕第10号（中国人民银行关于修改和废止部分规章的决定...",
      "documents": [
        {
          "type": "html",
          "url": "http://www.pbc.gov.cn/tiaofasi/144941/144957/5863650/index.html",
          "title": "中国人民银行令〔2025〕第10号（中国人民银行关于修改和废止部分规章的决定）",
          "downloaded": true,
          "local_path": "downloads/tiaofasi_departmental_rule/tiaofasi_departmental_rule_000107_001.html"
        }
      ]
    },
    {
      "serial": 12,
      "title": "中国人民银行 海关总署令〔2024〕第2号（关于废止《对金银进出国境的管理办法》的决定）",
      "remark": "中国人民银行 海关总署令〔2024〕第2号（关于废止《对金银进出国境的管理办...",
      "documents": [
        {
          "type": "html",
          "url": "http://www.pbc.gov.cn/tiaofasi/144941/144957/5271474/index.html",
          "title": "中国人民银行 海关总署令〔2024〕第2号（关于废止《对金银进出国境的管理办法》的决定）",
          "downloaded": true,
          "local_path": "downloads/tiaofasi_departmental_rule/tiaofasi_departmental_rule_000012_001.html"
        }
      ]
    },
    {
      "serial": 7,
      "title": "中国人民银行令〔2025〕第1号（中国人民银行关于废止部分规章的决定）",
      "remark": "2025-03-28",
      "documents": [
        {
          "type": "html",
          "url": "http://www.pbc.gov.cn/tiaofasi/144941/144957/5643270/index.html",
          "title": "中国人民银行令〔2025〕第1号（中国人民银行关于废止部分规章的决定）",
          "downloaded": true,
          "local_path": "downloads/tiaofasi_departmental_rule/tiaofasi_departmental_rule_000007_001.html"
        }
      ]
    },
    {
      "serial": 3,
      "title": "中国人民银行 国家金融监督管理总局令〔2025〕第6号（中国人民银行 国家金融监督管理总局关于废止《银行卡业务管理办法》的决定）",
      "remark": "中国人民银行 国家金融监督管理总局令〔2025〕第6号（中国人民银行 国家金融...",
      "documents": [
        {
          "type": "html",
          "url": "http://www.pbc.gov.cn/tiaofasi/144941/144957/5741321/index.html",
          "title": "中国人民银行 国家金融监督管理总局令〔2025〕第6号（中国人民银行 国家金融监督管理总局关于废止《银行卡业务管理办法》的决定）",
          "downloaded": true,
          "local_path": "downloads/tiaofasi_departmental_rule/tiaofasi_departmental_rule_000003_001.html"
        }
      ]
    },
    {
      "serial": 2,
      "title": "中国人民银行 财政部令〔2025〕第5号（中国人民银行 财政部关于废止《凭证式国债质押贷款办法》的决定）",
      "remark": "中国人民银行 财政部令〔2025〕第5号（中国人民银行 财政部关于废止《凭证式...",
      "documents": [
        {
          "type": "html",
          "url": "http://www.pbc.gov.cn/tiaofasi/144941/144957/5741168/index.html",
          "title": "中国人民银行 财政部令〔2025〕第5号（中国人民银行 财政部关于废止《凭证式国债质押贷款办法》的决定）",
          "downloaded": true,
          "local_path": "downloads/tiaofasi_departmental_rule/tiaofasi_departmental_rule_000002_001.html"
        }
      ]
    }
  ],
  "meta": {
    "dedupe": {
      "task": "tiaofasi_departmental_rule",
      "task_slug": "tiaofasi_departmental_rule",
      "source_state_file": "downloads/tiaofasi_departmental_rule_state.json",
      "generated_at": "2025-10-29T21:36:51",
      "original_entry_count": 109,
      "unique_entry_count": 106,
      "duplicate_entry_count": 3
    }
  }
}